buildkite_log_parse/__init__.py
buildkite_log_parse/fetch.py
buildkite_log_parse/main.py
buildkite_log_parse/parser.py
buildkite_log_parse/util.py
tests/__init__.py
tests/test_main.py
buildkite_log_parse-1.0.1.dist-info/LICENSE
buildkite_log_parse-1.0.1.dist-info/METADATA
buildkite_log_parse-1.0.1.dist-info/WHEEL
buildkite_log_parse-1.0.1.dist-info/entry_points.txt
buildkite_log_parse-1.0.1.dist-info/top_level.txt
buildkite_log_parse-1.0.1.dist-info/zip-safe
buildkite_log_parse-1.0.1.dist-info/RECORD
